skylos/__init__.py
skylos/analyzer.py
skylos/api.py
skylos/ast_mask.py
skylos/cli.py
skylos/codemods.py
skylos/compliance.py
skylos/config.py
skylos/constants.py
skylos/control_flow.py
skylos/credentials.py
skylos/fixer.py
skylos/gatekeeper.py
skylos/implicit_refs.py
skylos/known_patterns.py
skylos/linter.py
skylos/penalties.py
skylos/pyproject_entrypoints.py
skylos/pytest_unused_fixtures.py
skylos/sarif_exporter.py
skylos/server.py
skylos/sync.py
skylos/tracer.py
skylos/visitor.py
skylos/adapters/__init__.py
skylos/adapters/base.py
skylos/adapters/litellm_adapter.py
skylos/llm/__init__.py
skylos/llm/agents.py
skylos/llm/analyzer.py
skylos/llm/context.py
skylos/llm/merger.py
skylos/llm/prompts.py
skylos/llm/schemas.py
skylos/llm/ui.py
skylos/llm/validator.py
skylos/rules/__init__.py
skylos/rules/base.py
skylos/rules/custom.py
skylos/rules/secrets.py
skylos/rules/danger/__init__.py
skylos/rules/danger/calls.py
skylos/rules/danger/danger.py
skylos/rules/danger/taint.py
skylos/rules/danger/danger_cmd/__init__.py
skylos/rules/danger/danger_cmd/cmd_flow.py
skylos/rules/danger/danger_fs/__init__.py
skylos/rules/danger/danger_fs/path_flow.py
skylos/rules/danger/danger_hallucination/__init__.py
skylos/rules/danger/danger_hallucination/dependency_hallucination.py
skylos/rules/danger/danger_net/__init__.py
skylos/rules/danger/danger_net/ssrf_flow.py
skylos/rules/danger/danger_sql/__init__.py
skylos/rules/danger/danger_sql/sql_flow.py
skylos/rules/danger/danger_sql/sql_raw_flow.py
skylos/rules/danger/danger_web/__init__.py
skylos/rules/danger/danger_web/xss_flow.py
skylos/rules/quality/__init__.py
skylos/rules/quality/complexity.py
skylos/rules/quality/logic.py
skylos/rules/quality/nesting.py
skylos/rules/quality/performance.py
skylos/rules/quality/structure.py
skylos/rules/quality/unreachable.py
skylos/scale/__init__.py
skylos/scale/parallel_static.py
skylos/visitors/__init__.py
skylos/visitors/framework_aware.py
skylos/visitors/test_aware.py
skylos-3.1.2.dist-info/licenses/AUTHORS.md
skylos-3.1.2.dist-info/licenses/LICENSE
skylos-3.1.2.dist-info/METADATA
skylos-3.1.2.dist-info/WHEEL
skylos-3.1.2.dist-info/entry_points.txt
skylos-3.1.2.dist-info/top_level.txt
skylos-3.1.2.dist-info/RECORD
