Metadata-Version: 2.4
Name: skylos
Version: 3.1.2
Summary: An analysis tool for Python codebases
Author-email: oha <aaronoh2015@gmail.com>
Classifier: Development Status :: 4 - Beta
Classifier: Intended Audience :: Developers
Classifier: License :: OSI Approved :: Apache Software License
Classifier: Operating System :: OS Independent
Classifier: Programming Language :: Python :: 3
Classifier: Programming Language :: Python :: 3.10
Classifier: Programming Language :: Python :: 3.11
Classifier: Topic :: Software Development :: Quality Assurance
Classifier: Topic :: Software Development :: Testing
Requires-Python: >=3.10
License-File: LICENSE
License-File: AUTHORS.md
Requires-Dist: inquirer>=3.0.3
Requires-Dist: flask>=2.1.1
Requires-Dist: flask-cors>=3.0.3
Requires-Dist: libcst>=1.8.2
Requires-Dist: rich>=14.0.0
Requires-Dist: keyring>=25.7.0
Requires-Dist: requests
Requires-Dist: tree-sitter>=0.25.2
Requires-Dist: tree-sitter-typescript>=0.23.2
Requires-Dist: pyyaml
Requires-Dist: litellm
Dynamic: license-file
